{
  "posts": [
    {
      "userId": 1,
      "id": 1,
      "avatar": "",
      "nickname": "",
      "image": "",
      "title": "Здесь будет заголовок Вашего поста",
      "text": "Здесь будет основной текст Вашего поста"
    },
    {
      "id": 2,
      "user": "typicode",
      "title": "Здесь будет заголовок Вашего поста",
      "text": "Здесь будет основной текст Вашего поста"
    },
    {
      "id": 3,
      "user": "typicode",
      "title": "Здесь будет заголовок Вашего поста",
      "text": "Здесь будет основной текст Вашего поста"
    }
  ],
  "users": [
    {
      "userId": 1,
      "id": 1,
      "login": "some comment",
      "password": "qwerty",
      "token": "qwer123(20)$"
    }
  ]
}
